passwdgn/__init__.py
passwdgn/passwdgn.py
passwdgn-0.10.2.dist-info/LICENSE
passwdgn-0.10.2.dist-info/METADATA
passwdgn-0.10.2.dist-info/WHEEL
passwdgn-0.10.2.dist-info/top_level.txt
passwdgn-0.10.2.dist-info/RECORD
