Metadata-Version: 2.1
Name: passwdgn
Version: 0.10.2
Summary: A library to generate a password for registering on a website.
Author: Amirreza Soltani
Author-email: charleswestmorelandPB1@gmail.com
Classifier: Programming Language :: Python :: 3
Classifier: License :: OSI Approved :: MIT License
Classifier: Operating System :: Unix
Classifier: Operating System :: MacOS :: MacOS X
Classifier: Operating System :: Microsoft :: Windows
Requires-Python: >=3.6
License-File: LICENSE
